farpenpy-0.1.1.dist-info/METADATA
farpenpy-0.1.1.dist-info/WHEEL
farpenpy-0.1.1.dist-info/licenses/LICENSE
farpenpy/__init__.py
farpenpy/farpen.py
farpenpy/logger.py
farpenpy/subreports/__init__.py
farpenpy/subreports/apportionment.py
farpenpy-0.1.1.dist-info/RECORD
