Metadata-Version: 2.1
Name: farpenpy
Version: 0.1.1
Summary: FarpenPy Parser - Report Extractor
Author-Email: Jonhnatha Trigueiro <jon@preludian.com.br>
License: GNU Lesser General Public License v2.1
Requires-Python: >=3.10
Requires-Dist: pypdf>=4.2.0
Requires-Dist: pydantic>=2.7.4
Requires-Dist: pytest>=8.2.2; extra == "dev"
Requires-Dist: pytest-cov>=5.0.0; extra == "dev"
Requires-Dist: coverage>=7.5.4; extra == "dev"
Provides-Extra: dev
